README.md
setup.cfg
setup.py
instauto/__init__.py
instauto2.egg-info/PKG-INFO
instauto2.egg-info/SOURCES.txt
instauto2.egg-info/dependency_links.txt
instauto2.egg-info/requires.txt
instauto2.egg-info/top_level.txt
instauto/api/__init__.py
instauto/api/client.py
instauto/api/constants.py
instauto/api/exceptions.py
instauto/api/structs.py
instauto/api/actions/__init__.py
instauto/api/actions/authentication.py
instauto/api/actions/challenge.py
instauto/api/actions/friendships.py
instauto/api/actions/helpers.py
instauto/api/actions/post.py
instauto/api/actions/profile.py
instauto/api/actions/request.py
instauto/api/actions/search.py
instauto/api/actions/stubs.py
instauto/api/actions/structs/__init__.py
instauto/api/actions/structs/common.py
instauto/api/actions/structs/friendships.py
instauto/api/actions/structs/post.py
instauto/api/actions/structs/profile.py
instauto/api/actions/structs/search.py
instauto/api/actions/structs/tests/__init__.py
instauto/api/actions/tests/__init__.py
instauto/api/actions/tests/common.py
instauto/api/actions/tests/test_authentication.py
instauto/api/actions/tests/test_friendships.py
instauto/api/actions/tests/test_post.py
instauto/helpers/__init__.py
instauto/helpers/common.py
instauto/helpers/friendships.py
instauto/helpers/post.py
instauto/helpers/search.py
instauto/ready/__init__.py
instauto/ready/helpers.py
instauto/ready/interact_with_followers_of_account.py