Metadata-Version: 1.1
Name: instauto2
Version: 1.0.0
Summary: Python wrapper for the private Instagram API
Home-page: https://github.com/stanvanrooy/instauto
Author: Stan van Rooy
Author-email: stan@rooy.dev
License: MIT
Download-URL: https://github.com/stanvanrooy/instauto/archive/1.0.0.tar.gz
Keywords: instagram api,private instagram api
Platform: UNKNOWN
Classifier: Development Status :: 3 - Alpha
Classifier: Intended Audience :: Developers
Classifier: Topic :: Software Development :: Libraries :: Python Modules
Classifier: License :: OSI Approved :: GNU General Public License v3 (GPLv3)  
Classifier: Programming Language :: Python :: 3.8
Classifier: Programming Language :: Python :: 3.7
Classifier: Programming Language :: Python :: 3.6
